ManyChat/APIStructure.py
ManyChat/App.py
ManyChat/BaseAPI.py
ManyChat/__init__.py
ManyChat/api.py
ManyChat/fb/__init__.py
ManyChat/fb/page.py
ManyChat/fb/sending.py
ManyChat/fb/subscriber.py
manychat_api_python-0.0.1.dist-info/LICENSE
manychat_api_python-0.0.1.dist-info/METADATA
manychat_api_python-0.0.1.dist-info/WHEEL
manychat_api_python-0.0.1.dist-info/top_level.txt
manychat_api_python-0.0.1.dist-info/RECORD
