Metadata-Version: 2.1
Name: manychat-api-python
Version: 0.0.1
Summary: ManyChat API Python library
Home-page: https://github.com/manychat/manychat-api-python
Author: Yury Gavrilov
Author-email: yuriy@manychat.com
License: UNKNOWN
Platform: UNKNOWN
Classifier: Programming Language :: Python :: 3
Classifier: License :: OSI Approved :: MIT License
Classifier: Operating System :: OS Independent
Requires-Python: >=3.6
